{"name":"build-javascript","namedChunkGroups":{"polyfill":{"name":"polyfill","assets":[{"name":"webpack-runtime-171b2af8832e1eaaeda3.js","size":5273},{"name":"polyfill-e6f237514149a43a760b.js","size":85799}],"filteredAssets":0,"assetsSize":91072,"filteredAuxiliaryAssets":2,"auxiliaryAssetsSize":228279},"app":{"name":"app","assets":[{"name":"webpack-runtime-171b2af8832e1eaaeda3.js","size":5273},{"name":"styles.9a02dba6d25cd6643bc2.css","size":208685},{"name":"framework-fbee490e00ed74c17f40.js","size":130662},{"name":"app-2ee20bf908c40cdd0f2a.js","size":177785}],"filteredAssets":0,"assetsSize":522405,"filteredAuxiliaryAssets":54,"auxiliaryAssetsSize":2254883},"component---src-pages-404-js":{"name":"component---src-pages-404-js","assets":[{"name":"commons-a5c972690c08744f7112.js","size":113716},{"name":"component---src-pages-404-js-9e6fdfaa4e973f18650f.js","size":1590}],"filteredAssets":0,"assetsSize":115306,"filteredAuxiliaryAssets":2,"auxiliaryAssetsSize":469267},"component---src-pages-about-js":{"name":"component---src-pages-about-js","assets":[{"name":"commons-a5c972690c08744f7112.js","size":113716},{"name":"component---src-pages-about-js-1505b5b6c231e6f065c3.js","size":6497}],"filteredAssets":0,"assetsSize":120213,"filteredAuxiliaryAssets":3,"auxiliaryAssetsSize":574278},"component---src-pages-blog-contentful-blog-post-title-js":{"name":"component---src-pages-blog-contentful-blog-post-title-js","assets":[{"name":"styles.9a02dba6d25cd6643bc2.css","size":208685},{"name":"commons-a5c972690c08744f7112.js","size":113716},{"name":"component---src-pages-blog-contentful-blog-post-title-js-03e6e49d99fff0a181c2.js","size":4891}],"filteredAssets":0,"assetsSize":327292,"filteredAuxiliaryAssets":53,"auxiliaryAssetsSize":1601033},"component---src-pages-blog-js":{"name":"component---src-pages-blog-js","assets":[{"name":"commons-a5c972690c08744f7112.js","size":113716},{"name":"component---src-pages-blog-js-7503fff9203c283567a5.js","size":4065}],"filteredAssets":0,"assetsSize":117781,"filteredAuxiliaryAssets":2,"auxiliaryAssetsSize":478998},"component---src-pages-index-js":{"name":"component---src-pages-index-js","assets":[{"name":"commons-a5c972690c08744f7112.js","size":113716},{"name":"component---src-pages-index-js-24fe649739c9bf90f06f.js","size":144841}],"filteredAssets":0,"assetsSize":258557,"filteredAuxiliaryAssets":3,"auxiliaryAssetsSize":1292144},"component---src-pages-team-js":{"name":"component---src-pages-team-js","assets":[{"name":"commons-a5c972690c08744f7112.js","size":113716},{"name":"component---src-pages-team-js-7a9cdfae4208c08986fd.js","size":57985}],"filteredAssets":0,"assetsSize":171701,"filteredAuxiliaryAssets":9,"auxiliaryAssetsSize":1711082}},"assetsByChunkName":{"polyfill":["webpack-runtime-171b2af8832e1eaaeda3.js","polyfill-e6f237514149a43a760b.js"],"app":["webpack-runtime-171b2af8832e1eaaeda3.js","styles.9a02dba6d25cd6643bc2.css","framework-fbee490e00ed74c17f40.js","app-2ee20bf908c40cdd0f2a.js"],"component---src-pages-404-js":["commons-a5c972690c08744f7112.js","component---src-pages-404-js-9e6fdfaa4e973f18650f.js"],"component---src-pages-about-js":["commons-a5c972690c08744f7112.js","component---src-pages-about-js-1505b5b6c231e6f065c3.js"],"component---src-pages-blog-contentful-blog-post-title-js":["styles.9a02dba6d25cd6643bc2.css","commons-a5c972690c08744f7112.js","component---src-pages-blog-contentful-blog-post-title-js-03e6e49d99fff0a181c2.js"],"component---src-pages-blog-js":["commons-a5c972690c08744f7112.js","component---src-pages-blog-js-7503fff9203c283567a5.js"],"component---src-pages-index-js":["commons-a5c972690c08744f7112.js","component---src-pages-index-js-24fe649739c9bf90f06f.js"],"component---src-pages-team-js":["commons-a5c972690c08744f7112.js","component---src-pages-team-js-7a9cdfae4208c08986fd.js"]},"childAssetsByChunkName":{}}