{"name":"build-javascript","namedChunkGroups":{"polyfill":{"name":"polyfill","assets":[{"name":"webpack-runtime-0c862d949faf9c0a34da.js","size":5146},{"name":"polyfill-e6f237514149a43a760b.js","size":85799}],"filteredAssets":0,"assetsSize":90945,"filteredAuxiliaryAssets":2,"auxiliaryAssetsSize":228080},"app":{"name":"app","assets":[{"name":"webpack-runtime-0c862d949faf9c0a34da.js","size":5146},{"name":"styles.9a02dba6d25cd6643bc2.css","size":208685},{"name":"framework-fbee490e00ed74c17f40.js","size":130662},{"name":"app-21ddb16e912d232fd093.js","size":177337}],"filteredAssets":0,"assetsSize":521830,"filteredAuxiliaryAssets":54,"auxiliaryAssetsSize":2254188},"component---src-pages-404-js":{"name":"component---src-pages-404-js","assets":[{"name":"commons-318014495fb7aab0346e.js","size":92061},{"name":"component---src-pages-404-js-7b1a318b450f33f9939d.js","size":1590}],"filteredAssets":0,"assetsSize":93651,"filteredAuxiliaryAssets":2,"auxiliaryAssetsSize":379377},"component---src-pages-blog-contentful-blog-post-title-js":{"name":"component---src-pages-blog-contentful-blog-post-title-js","assets":[{"name":"styles.9a02dba6d25cd6643bc2.css","size":208685},{"name":"commons-318014495fb7aab0346e.js","size":92061},{"name":"component---src-pages-blog-contentful-blog-post-title-js-f53701b12b37ab4720e2.js","size":4986}],"filteredAssets":0,"assetsSize":305732,"filteredAuxiliaryAssets":53,"auxiliaryAssetsSize":1511184},"component---src-pages-blog-js":{"name":"component---src-pages-blog-js","assets":[{"name":"commons-318014495fb7aab0346e.js","size":92061},{"name":"component---src-pages-blog-js-3e0c94bb75c30b8d9bdd.js","size":4065}],"filteredAssets":0,"assetsSize":96126,"filteredAuxiliaryAssets":2,"auxiliaryAssetsSize":389108},"component---src-pages-index-js":{"name":"component---src-pages-index-js","assets":[{"name":"commons-318014495fb7aab0346e.js","size":92061},{"name":"component---src-pages-index-js-9d606803e642174c0ba6.js","size":188316}],"filteredAssets":0,"assetsSize":280377,"filteredAuxiliaryAssets":12,"auxiliaryAssetsSize":2422678}},"assetsByChunkName":{"polyfill":["webpack-runtime-0c862d949faf9c0a34da.js","polyfill-e6f237514149a43a760b.js"],"app":["webpack-runtime-0c862d949faf9c0a34da.js","styles.9a02dba6d25cd6643bc2.css","framework-fbee490e00ed74c17f40.js","app-21ddb16e912d232fd093.js"],"component---src-pages-404-js":["commons-318014495fb7aab0346e.js","component---src-pages-404-js-7b1a318b450f33f9939d.js"],"component---src-pages-blog-contentful-blog-post-title-js":["styles.9a02dba6d25cd6643bc2.css","commons-318014495fb7aab0346e.js","component---src-pages-blog-contentful-blog-post-title-js-f53701b12b37ab4720e2.js"],"component---src-pages-blog-js":["commons-318014495fb7aab0346e.js","component---src-pages-blog-js-3e0c94bb75c30b8d9bdd.js"],"component---src-pages-index-js":["commons-318014495fb7aab0346e.js","component---src-pages-index-js-9d606803e642174c0ba6.js"]},"childAssetsByChunkName":{}}